dagmar_adform_api_wrapper/__init__.py
dagmar_adform_api_wrapper/__version__.py
dagmar_adform_api_wrapper/api.py
dagmar_adform_api_wrapper/status.py
dagmar_adform_api_wrapper-1.0.0.dist-info/LICENSE
dagmar_adform_api_wrapper-1.0.0.dist-info/METADATA
dagmar_adform_api_wrapper-1.0.0.dist-info/WHEEL
dagmar_adform_api_wrapper-1.0.0.dist-info/top_level.txt
dagmar_adform_api_wrapper-1.0.0.dist-info/RECORD
