Metadata-Version: 2.1
Name: dagmar-adform-api-wrapper
Version: 1.0.0
Summary: Python Adform API wrapper
Home-page: https://github.com/tkatva/adform-api-wrapper
Author: Tuomas Katva
Author-email: tuomas.katva@dagmar.fi
License: MIT
Platform: UNKNOWN
Classifier: License :: OSI Approved :: MIT License
Classifier: Programming Language :: Python
Classifier: Programming Language :: Python :: 3
Classifier: Programming Language :: Python :: 3.6
Classifier: Programming Language :: Python :: Implementation :: CPython
Classifier: Programming Language :: Python :: Implementation :: PyPy
Requires-Python: >=3.7
Requires-Dist: requests (>=2.21.0)
